trieve_client/__init__.py
trieve_client/api/__init__.py
trieve_client/api/auth/__init__.py
trieve_client/api/auth/callback.py
trieve_client/api/auth/get_me.py
trieve_client/api/auth/login.py
trieve_client/api/auth/logout.py
trieve_client/api/chunk/__init__.py
trieve_client/api/chunk/create_chunk.py
trieve_client/api/chunk/create_suggested_queries_handler.py
trieve_client/api/chunk/delete_chunk.py
trieve_client/api/chunk/delete_chunk_by_tracking_id.py
trieve_client/api/chunk/generate_off_chunks.py
trieve_client/api/chunk/get_chunk_by_id.py
trieve_client/api/chunk/get_chunk_by_tracking_id.py
trieve_client/api/chunk/get_recommended_chunks.py
trieve_client/api/chunk/search_chunk.py
trieve_client/api/chunk/update_chunk.py
trieve_client/api/chunk/update_chunk_by_tracking_id.py
trieve_client/api/chunk_group/__init__.py
trieve_client/api/chunk_group/add_bookmark.py
trieve_client/api/chunk_group/create_chunk_group.py
trieve_client/api/chunk_group/delete_bookmark.py
trieve_client/api/chunk_group/delete_chunk_group.py
trieve_client/api/chunk_group/get_all_bookmarks.py
trieve_client/api/chunk_group/get_groups_chunk_is_in.py
trieve_client/api/chunk_group/get_specific_dataset_chunk_groups.py
trieve_client/api/chunk_group/search_groups.py
trieve_client/api/chunk_group/search_over_groups.py
trieve_client/api/chunk_group/update_chunk_group.py
trieve_client/api/dataset/__init__.py
trieve_client/api/dataset/create_dataset.py
trieve_client/api/dataset/delete_dataset.py
trieve_client/api/dataset/get_client_dataset_config.py
trieve_client/api/dataset/get_dataset.py
trieve_client/api/dataset/get_datasets_from_organization.py
trieve_client/api/dataset/update_dataset.py
trieve_client/api/events/__init__.py
trieve_client/api/events/get_events.py
trieve_client/api/file/__init__.py
trieve_client/api/file/delete_file_handler.py
trieve_client/api/file/get_file_handler.py
trieve_client/api/file/get_image_file.py
trieve_client/api/file/upload_file_handler.py
trieve_client/api/health/__init__.py
trieve_client_py-0.3.21.dist-info/METADATA
trieve_client_py-0.3.21.dist-info/WHEEL
trieve_client_py-0.3.21.dist-info/RECORD
