Metadata-Version: 2.1
Name: trieve_client_py
Version: 0.3.21
Summary: Python client library for trieve.ai
Author: Denzell Ford
Author-email: denzell.f@trieve.ai
Requires-Python: >=3.8,<4.0
Classifier: Programming Language :: Python :: 3
Classifier: Programming Language :: Python :: 3.8
Classifier: Programming Language :: Python :: 3.9
Classifier: Programming Language :: Python :: 3.10
Classifier: Programming Language :: Python :: 3.11
Classifier: Programming Language :: Python :: 3.12
Requires-Dist: attrs (>=21.3.0)
Requires-Dist: httpx (>=0.20.0,<0.27.0)
Requires-Dist: python-dateutil (>=2.8.0,<3.0.0)
